{"stat.useItem.minecraft.bow":863,"stat.pickup.minecraft.repeating_command_block":1,"stat.drop.minecraft.dark_oak_boat":3,"stat.useItem.minecraft.quartz_block":1439,"stat.pickup.minecraft.wooden_slab":8,"stat.leaveGame":92,"stat.drop.minecraft.redstone":4,"stat.useItem.minecraft.glowstone":491,"stat.pickup.minecraft.dark_oak_boat":1,"stat.pickup.minecraft.rotten_flesh":10,"stat.useItem.minecraft.diamond_hoe":170,"stat.useItem.minecraft.sandstone_stairs":2,"stat.drop.minecraft.leather_boots":2,"stat.useItem.minecraft.birch_boat":344,"stat.pickup.minecraft.bucket":1,"stat.useItem.minecraft.rail":36,"stat.pickup.minecraft.leather_boots":1,"stat.drop.minecraft.elytra":70,"stat.useItem.minecraft.anvil":2,"stat.drop.minecraft.sand":1,"stat.killEntity.MushroomCow":20,"stat.useItem.minecraft.nether_wart":7,"stat.furnaceInteraction":9,"stat.useItem.minecraft.pumpkin_seeds":6,"stat.pickup.minecraft.nether_brick":5,"stat.drop.minecraft.chorus_fruit":1,"stat.noteblockPlayed":25,"stat.pickup.minecraft.sponge":3,"stat.useItem.minecraft.end_stone":16,"stat.pickup.minecraft.beef":18,"stat.useItem.minecraft.blue_shulker_box":1,"stat.useItem.minecraft.trapdoor":323,"stat.pickup.minecraft.cyan_shulker_box":2,"stat.useItem.minecraft.stained_glass":716,"stat.useItem.minecraft.fence":85,"stat.useItem.minecraft.dark_oak_door":22,"stat.useItem.minecraft.ice":286,"stat.useItem.minecraft.cauldron":8,"stat.useItem.minecraft.wheat_seeds":62,"stat.pickup.minecraft.emerald":18,"stat.useItem.minecraft.dye":90,"stat.pickup.minecraft.lever":5,"stat.deaths":220,"stat.pickup.minecraft.egg":2,"stat.useItem.minecraft.nether_brick":1021,"stat.pickup.minecraft.item_frame":5,"stat.chestOpened":140,"stat.useItem.minecraft.splash_potion":196,"stat.drop.minecraft.birch_fence_gate":1,"stat.useItem.minecraft.stone":2110,"stat.useItem.minecraft.jungle_fence":153,"stat.pickup.minecraft.arrow":8,"stat.pickup.minecraft.structure_void":2,"stat.pickup.minecraft.wooden_pressure_plate":3,"stat.useItem.minecraft.ender_chest":14,"stat.useItem.minecraft.white_shulker_box":6,"stat.drop.minecraft.dark_oak_stairs":8,"stat.crouchOneCm":170659,"stat.craftingTableInteraction":3,"stat.pickup.minecraft.nether_brick_fence":3,"stat.useItem.minecraft.light_blue_shulker_box":2,"stat.pickup.minecraft.repeater":13,"stat.useItem.minecraft.dark_oak_fence":178,"stat.pickup.minecraft.planks":1105,"stat.drop.minecraft.minecart":33,"stat.drop.minecraft.jungle_fence":1,"stat.pickup.minecraft.wheat_seeds":3,"stat.drop.minecraft.snow":1,"stat.drop.minecraft.soul_sand":3,"stat.useItem.minecraft.enchanting_table":10,"stat.drop.minecraft.carpet":9,"stat.pickup.minecraft.ice":1,"stat.killEntity.VindicationIllager":33,"stat.flowerPotted":1,"stat.pickup.minecraft.light_blue_shulker_box":2,"stat.useItem.minecraft.cobblestone":89,"stat.useItem.minecraft.gravel":1,"stat.minecartOneCm":682862,"stat.drop.minecraft.coal_ore":1,"stat.pickup.minecraft.bedrock":2,"stat.drop.minecraft.glass_pane":1,"stat.drop.minecraft.iron_ore":2,"stat.pickup.minecraft.tipped_arrow":3,"stat.drop.minecraft.brick_stairs":1,"stat.useItem.minecraft.fireworks":32,"stat.useItem.minecraft.glass_pane":12,"stat.useItem.minecraft.barrier":509,"stat.useItem.minecraft.acacia_boat":1,"stat.drop.minecraft.hopper_minecart":2,"stat.useItem.minecraft.stonebrick":423,"stat.useItem.minecraft.wooden_door":4,"stat.useItem.minecraft.grass_path":219,"stat.useItem.minecraft.monster_egg":47,"stat.drop.minecraft.leather_leggings":1,"stat.pickup.minecraft.red_nether_brick":2,"stat.drop.minecraft.sea_lantern":65,"stat.useItem.minecraft.wooden_axe":2,"stat.drop.minecraft.grass":7,"stat.drop.minecraft.totem_of_undying":3,"stat.pickup.minecraft.bookshelf":1,"stat.useItem.minecraft.skull":273,"stat.useItem.minecraft.snow":596,"stat.useItem.minecraft.concrete_powder":118,"stat.pickup.minecraft.glowstone":4,"stat.useItem.minecraft.chorus_flower":4,"stat.useItem.minecraft.coal_block":15,"stat.craftItem.minecraft.arrow":1,"stat.pickup.minecraft.sticky_piston":2,"stat.useItem.minecraft.obsidian":23,"stat.pickup.minecraft.bow":3,"stat.drop.minecraft.birch_boat":2,"stat.useItem.minecraft.egg":667,"stat.pickup.minecraft.coal_ore":1,"stat.drop.minecraft.quartz_stairs":3,"stat.craftItem.minecraft.bow":1,"stat.pickup.minecraft.diamond_hoe":4,"stat.pickup.minecraft.diamond_leggings":8,"stat.flyOneCm":18529495,"stat.pickup.minecraft.nether_brick_stairs":3,"stat.pickup.minecraft.fish":11,"stat.timeSinceDeath":0,"stat.cauldronFilled":1,"stat.useItem.minecraft.wooden_slab":1803,"stat.drop.minecraft.repeater":1,"stat.useItem.minecraft.potato":5,"stat.pickup.minecraft.nether_wart":2,"stat.drop.minecraft.stained_glass":1618,"stat.killEntity.Wolf":58,"stat.drop.minecraft.wool":4,"stat.drop.minecraft.spawn_egg":3,"stat.useItem.minecraft.milk_bucket":25,"stat.drop.minecraft.birch_fence":2,"stat.drop.minecraft.jungle_stairs":1,"stat.pickup.minecraft.birch_stairs":1,"stat.sprintOneCm":3548245,"stat.useItem.minecraft.diamond_block":160,"stat.drop.minecraft.leather":1,"stat.drop.minecraft.dark_oak_door":5,"stat.useItem.minecraft.snowball":259,"stat.entityKilledBy.VindicationIllager":1,"stat.drop.minecraft.lava_bucket":2,"stat.drop.minecraft.boat":5,"stat.pickup.minecraft.spawn_egg":1,"stat.drop.minecraft.redstone_ore":3,"stat.craftItem.minecraft.golden_sword":1,"stat.drop.minecraft.golden_rail":1,"stat.useItem.minecraft.ladder":59,"stat.useItem.minecraft.cyan_shulker_box":1,"stat.killEntity.Zombie":10,"stat.useItem.minecraft.birch_stairs":70,"stat.diveOneCm":160778,"stat.craftItem.minecraft.sandstone":64,"stat.useItem.minecraft.sticky_piston":15,"stat.drop.minecraft.purpur_stairs":1,"stat.pickup.minecraft.sign":2,"stat.drop.minecraft.dark_oak_fence":4,"stat.drop.minecraft.bookshelf":2,"stat.drop.minecraft.ladder":2,"stat.useItem.minecraft.tnt_minecart":407,"stat.pickup.minecraft.stained_glass_pane":4,"stat.useItem.minecraft.heavy_weighted_pressure_plate":28,"stat.drop.minecraft.sponge":3,"stat.jump":11639,"stat.useItem.minecraft.iron_trapdoor":26,"stat.pickup.minecraft.white_shulker_box":2,"stat.pickup.minecraft.iron_ingot":41,"stat.useItem.minecraft.dark_oak_boat":194,"stat.pickup.minecraft.hopper_minecart":1,"stat.drop.minecraft.diamond_sword":2,"stat.pickup.minecraft.dirt":23,"stat.useItem.minecraft.coal_ore":10,"stat.drop.minecraft.glowstone":66,"stat.useItem.minecraft.dispenser":1,"stat.useItem.minecraft.glass":19,"stat.drop.minecraft.barrier":68,"stat.pickup.minecraft.gold_ore":1,"stat.pickup.minecraft.iron_axe":6,"stat.drop.minecraft.acacia_boat":1,"stat.damageTaken":245546,"stat.useItem.minecraft.stone_brick_stairs":75,"stat.useItem.minecraft.gold_block":11,"stat.tradedWithVillager":36,"stat.noteblockTuned":75,"stat.pickup.minecraft.log2":10,"stat.drop.minecraft.nether_star":66,"stat.useItem.minecraft.birch_fence":42,"stat.killEntity.Shulker":1,"stat.useItem.minecraft.snow_layer":213,"stat.killEntity.Silverfish":22,"stat.useItem.minecraft.chest":133,"stat.useItem.minecraft.observer":30,"stat.useItem.minecraft.tnt":17,"stat.useItem.minecraft.gold_ore":7,"stat.useItem.minecraft.lava_bucket":177,"stat.drop.minecraft.birch_stairs":3,"stat.useItem.minecraft.item_frame":29,"stat.useItem.minecraft.birch_fence_gate":4,"stat.shulkerBoxOpened":13,"stat.drop.minecraft.potato":1,"stat.useItem.minecraft.stained_hardened_clay":135,"stat.drop.minecraft.egg":1,"stat.drop.minecraft.wooden_slab":14,"stat.useItem.minecraft.netherrack":34,"stat.mineBlock.minecraft.tnt":1,"stat.drop.minecraft.nether_brick":1,"stat.drop.minecraft.lever":1,"stat.pickup.minecraft.dark_oak_stairs":7,"stat.mobKills":205,"stat.pickup.minecraft.diamond_boots":13,"stat.drop.minecraft.written_book":1,"stat.pickup.minecraft.diamond":2,"stat.pickup.minecraft.torch":1,"stat.drop.minecraft.quartz_block":4,"stat.drop.minecraft.arrow":96,"stat.useItem.minecraft.bookshelf":72,"stat.useItem.minecraft.soul_sand":15,"stat.useItem.minecraft.repeating_command_block":9,"stat.drop.minecraft.trapdoor":1,"stat.drop.minecraft.skull":9,"stat.useItem.minecraft.planks":1742,"stat.useItem.minecraft.nether_brick_stairs":448,"stat.pickup.minecraft.glass":368,"stat.useItem.minecraft.water_bucket":931,"stat.pickup.minecraft.sand":11,"stat.useItem.minecraft.golden_sword":6,"stat.useItem.minecraft.red_nether_brick":518,"stat.aviateOneCm":2127098,"stat.hopperInspected":43,"stat.useItem.minecraft.spawn_egg":134,"stat.pickup.minecraft.packed_ice":1,"stat.useItem.minecraft.red_glazed_terracotta":1,"stat.trappedChestTriggered":5,"stat.drop.minecraft.rail":2,"stat.useItem.minecraft.oak_stairs":59,"stat.drop.minecraft.diamond_block":65,"stat.useItem.minecraft.dark_oak_stairs":648,"stat.drop.minecraft.stone_slab":7,"stat.pickup.minecraft.filled_map":67,"stat.useItem.minecraft.minecart":115,"stat.useItem.minecraft.redstone":37,"stat.drop.minecraft.stained_hardened_clay":2,"stat.pickup.minecraft.totem_of_undying":2,"stat.drop.minecraft.monster_egg":9,"stat.useItem.minecraft.stone_stairs":105,"stat.pickup.minecraft.skull":3,"stat.drop.minecraft.acacia_stairs":1,"stat.drop.minecraft.fireworks":64,"stat.playOneMinute":2931798,"stat.useItem.minecraft.jungle_stairs":222,"stat.drop.minecraft.chest":2071,"stat.pickup.minecraft.netherrack":2,"stat.useItem.minecraft.packed_ice":189,"stat.fallOneCm":3476013,"stat.drop.minecraft.stone":9,"stat.drop.minecraft.gold_ore":2,"stat.useItem.minecraft.nether_brick_fence":117,"stat.drop.minecraft.stained_glass_pane":5,"stat.dropperInspected":11,"stat.drop.minecraft.structure_void":2,"stat.useItem.minecraft.golden_rail":113,"stat.pickup.minecraft.feather":1,"stat.useItem.minecraft.furnace":19,"stat.pickup.minecraft.monster_egg":9,"stat.killEntity.Llama":1,"stat.drop.minecraft.diamond_hoe":4,"stat.useItem.minecraft.wool":913,"stat.pickup.minecraft.redstone_ore":1,"stat.useItem.minecraft.iron_bars":85,"stat.drop.minecraft.tnt_minecart":16,"stat.drop.minecraft.iron_axe":4,"stat.pickup.minecraft.flint_and_steel":1,"stat.useItem.minecraft.log":1277,"stat.drop.minecraft.end_stone":2,"stat.drop.minecraft.sign":1,"stat.drop.minecraft.stonebrick":7,"stat.drop.minecraft.planks":2363,"stat.drop.minecraft.lapis_block":1,"stat.pickup.minecraft.sapling":6,"stat.pickup.minecraft.wooden_door":8,"stat.useItem.minecraft.birch_door":12,"stat.drop.minecraft.bow":5,"stat.pickup.minecraft.diamond_helmet":8,"stat.useItem.minecraft.wooden_pressure_plate":5,"stat.drop.minecraft.birch_door":1,"stat.useItem.minecraft.beetroot_seeds":2,"stat.sneakTime":100229,"stat.pickup.minecraft.stone_slab":5,"stat.pickup.minecraft.golden_rail":2,"stat.drop.minecraft.wooden_axe":6,"stat.pickup.minecraft.chest":2160,"stat.useItem.minecraft.lapis_block":147,"stat.pickup.minecraft.bone":27,"stat.pickup.minecraft.stone_pressure_plate":61,"stat.horseOneCm":787,"stat.useItem.minecraft.log2":777,"stat.drop.minecraft.red_mushroom":3,"stat.drop.minecraft.leather_helmet":1,"stat.useItem.minecraft.diamond_sword":375,"stat.swimOneCm":86325,"stat.climbOneCm":34760,"stat.drop.minecraft.sticky_piston":2,"stat.enderchestOpened":10,"stat.useItem.minecraft.dirt":3449,"stat.pickup.minecraft.anvil":1,"stat.drop.minecraft.iron_trapdoor":45,"stat.useItem.minecraft.iron_ore":10,"stat.pickup.minecraft.tnt_minecart":20,"stat.pickup.minecraft.quartz_stairs":2,"stat.pickup.minecraft.soul_sand":2,"stat.drop.minecraft.wheat_seeds":2,"stat.pickup.minecraft.acacia_boat":2,"stat.pickup.minecraft.redstone":10,"stat.useItem.minecraft.sign":67,"stat.drop.minecraft.log":4,"stat.useItem.minecraft.lever":49,"stat.pickup.minecraft.wooden_axe":7,"stat.pickup.minecraft.dark_oak_door":8,"stat.pickup.minecraft.stonebrick":3,"stat.drop.minecraft.dirt":6,"stat.pickup.minecraft.carpet":54,"stat.useItem.minecraft.acacia_stairs":159,"stat.useItem.minecraft.chest_minecart":68,"stat.drop.minecraft.bedrock":2,"stat.useItem.minecraft.purpur_pillar":104,"stat.drop.minecraft.log2":11,"stat.useItem.minecraft.sea_lantern":690,"stat.pickup.minecraft.nether_star":4,"stat.pickup.minecraft.paper":2,"stat.craftItem.minecraft.stick":1,"stat.useItem.minecraft.stone_slab":1401,"stat.useItem.minecraft.bed":7,"stat.pickup.minecraft.grass":6,"stat.drop.minecraft.leaves":3,"stat.useItem.minecraft.carrot":5,"stat.killEntity.Endermite":7,"stat.pickup.minecraft.diamond_chestplate":8,"stat.useItem.minecraft.bucket":144,"stat.drop.minecraft.tipped_arrow":1,"stat.pickup.minecraft.blue_shulker_box":1,"stat.drop":1340,"stat.pickup.minecraft.stone_button":2,"stat.drop.minecraft.redstone_block":1,"stat.useItem.minecraft.melon_seeds":6,"stat.useItem.minecraft.structure_void":30,"stat.useItem.minecraft.quartz_stairs":337,"stat.pickup.minecraft.gravel":2,"stat.useItem.minecraft.diamond_axe":86,"stat.useItem.minecraft.waterlily":30,"stat.useItem.minecraft.black_glazed_terracotta":2,"stat.useItem.minecraft.carpet":900,"stat.useItem.minecraft.stained_glass_pane":427,"stat.pickup.minecraft.diamond_sword":2,"stat.pickup.minecraft.brick":262,"stat.useItem.minecraft.bedrock":110,"stat.useItem.minecraft.piston":44,"stat.useItem.minecraft.stone_button":4,"stat.drop.minecraft.piston":3,"stat.drop.minecraft.glass":452,"stat.pickup.minecraft.iron_ore":1,"stat.pickup.minecraft.snow":3,"stat.boatOneCm":87003,"stat.useItem.minecraft.redstone_lamp":4,"stat.pickup.minecraft.leaves":1,"stat.pickup.minecraft.leather":9,"stat.dispenserInspected":6,"stat.pickup.minecraft.dark_oak_fence":4,"stat.drop.minecraft.stone_button":1,"stat.drop.minecraft.water_bucket":4,"stat.pickup.minecraft.reeds":2,"stat.pickup.minecraft.oak_stairs":2,"stat.pickup.minecraft.stained_glass":215,"stat.damageDealt":22270,"stat.sleepInBed":4,"stat.killEntity.Cow":4,"stat.pickup.minecraft.minecart":92,"stat.pickup.minecraft.piston":10,"stat.pickup.minecraft.boat":5,"stat.walkOneCm":8159327,"stat.playerKills":51,"stat.useItem.minecraft.dark_oak_fence_gate":8,"stat.useItem.minecraft.redstone_block":71,"stat.pickup.minecraft.tnt":199,"stat.drop.minecraft.leather_chestplate":1,"stat.pickup.minecraft.stone":68,"stat.drop.minecraft.emerald":18,"stat.useItem.minecraft.leaves":832,"stat.pickup.minecraft.chorus_fruit":18,"stat.pickup.minecraft.gold_ingot":58,"stat.pickup.minecraft.barrier":68,"stat.killEntity.Chicken":25,"stat.useItem.minecraft.iron_block":248,"stat.drop.minecraft.repeating_command_block":1,"stat.pickup.minecraft.water_bucket":2,"stat.useItem.minecraft.hopper_minecart":202,"stat.pickup.minecraft.elytra":33,"stat.pickup.minecraft.lava_bucket":1,"stat.drop.minecraft.beef":10,"stat.useItem.minecraft.sandstone":105}